macrosignage/__init__.py
macrosignage/config.py
macrosignage/extensions.py
macrosignage/blueprints/__init__.py
macrosignage/blueprints/core/__init__.py
macrosignage/blueprints/core/forms.py
macrosignage/blueprints/core/models.py
macrosignage/blueprints/core/templates/core/display.html
macrosignage/blueprints/core/templates/core/display_list.html
macrosignage/blueprints/core/templates/core/display_slides.html
macrosignage/blueprints/core/templates/core/index.html
macrosignage/blueprints/core/templates/core/slides.html
macrosignage/ui/static/css/animate.css
macrosignage/ui/static/css/animate.min.css
macrosignage/ui/static/css/icons.css
macrosignage/ui/static/css/icons.min.css
macrosignage/ui/static/css/main.css
macrosignage/ui/static/css/main.min.css
macrosignage/ui/static/css/materialize.css
macrosignage/ui/static/css/materialize.min.css
macrosignage/ui/static/js/main.js
macrosignage/ui/static/js/main.min.js
macrosignage/ui/static/js/materialize.js
macrosignage/ui/static/js/materialize.min.js
macrosignage/ui/templates/layouts/base.html
macrosignage/utils/__init__.py
macrosignage/utils/sql.py
MacroSignage-0.1.dev36.dist-info/LICENSE
MacroSignage-0.1.dev36.dist-info/METADATA
MacroSignage-0.1.dev36.dist-info/WHEEL
MacroSignage-0.1.dev36.dist-info/top_level.txt
MacroSignage-0.1.dev36.dist-info/RECORD
